deepfake/__init__.py
deepfake/classifiers.py
deepfake/deepfake.py
deepfake/kernel_utils.py
towhee_deepfake-0.0.3.dist-info/LICENSE
towhee_deepfake-0.0.3.dist-info/METADATA
towhee_deepfake-0.0.3.dist-info/WHEEL
towhee_deepfake-0.0.3.dist-info/top_level.txt
towhee_deepfake-0.0.3.dist-info/RECORD
