Metadata-Version: 2.1
Name: towhee-deepfake
Version: 0.0.3
Summary: Deepfake
Home-page: https://towhee.io/towhee/deepfake
Author: Zhuoran Yu
Author-email: zhuoran.yu@zilliz.com
Classifier: Programming Language :: Python :: 3
Classifier: License :: OSI Approved :: MIT License
Classifier: Operating System :: OS Independent
License-File: LICENSE
Requires-Dist: cmake
Requires-Dist: dlib
Requires-Dist: facenet-pytorch
Requires-Dist: albumentations
Requires-Dist: timm
Requires-Dist: pytorch-toolbelt
Requires-Dist: tensorboardx
Requires-Dist: matplotlib
Requires-Dist: tqdm
Requires-Dist: pandas
